dask_sphinx_theme/__init__.py
dask_sphinx_theme/_version.py
dask_sphinx_theme/layout.html
dask_sphinx_theme/theme.conf
dask_sphinx_theme/_pygments/style.py
dask_sphinx_theme/ext/dask_config_sphinx_ext.py
dask_sphinx_theme/static/css/style.css
dask_sphinx_theme/static/images/background-grid.svg
dask_sphinx_theme/static/images/dask-horizontal-white.svg
dask_sphinx_theme/static/images/favicon.ico
dask_sphinx_theme/static/images/favicon.svg
dask_sphinx_theme/static/images/icon-download.svg
dask_sphinx_theme/static/images/icon-expand.svg
dask_sphinx_theme/static/images/icon-menu.svg
dask_sphinx_theme/static/js/custom.js
dask_sphinx_theme-4.0.0.dist-info/METADATA
dask_sphinx_theme-4.0.0.dist-info/WHEEL
dask_sphinx_theme-4.0.0.dist-info/entry_points.txt
dask_sphinx_theme-4.0.0.dist-info/licenses/LICENSE.txt
dask_sphinx_theme-4.0.0.dist-info/RECORD
