Metadata-Version: 2.4
Name: dask_sphinx_theme
Version: 4.0.0
Summary: Dask theme for Sphinx
Project-URL: Homepage, https://github.com/dask/dask-sphinx-theme/
Author: Dask Developers
License: BSD
License-File: LICENSE.txt
Requires-Python: >=3.11
Requires-Dist: jsonschema
Requires-Dist: numpydoc
Requires-Dist: pyyaml
Requires-Dist: sphinx-book-theme<2,>=1
Requires-Dist: sphinx>=7.0
